[
  {
    "id": "cert-1765680705484",
    "type": "cert",
    "date": "2025-12-14",
    "filename": "Certificate file",
    "check": "🟢 Good",
    "certname": "Wasu Media & Network",
    "size": "p12, .mobileprovision",
    "downloadUrl": "https://www.mediafire.com/file/apn55m26wdkl55m/Wasu+Media+++Network+Co.,+Ltd.zip/file",
    "iconUrl": "https://cdn-icons-png.freepik.com/256/6572/6572271.png?semt=ais_white_label",
    "tag": "NEW"
  },
  {
    "id": 1,
    "filename": "Certificate file",
    "check": "Trạng  thái: 🟢 Good",
    "certname": "Etisalat - Emirates Telecommunications Corporation",
    "size": " .p12, .mobileprovision",
    "downloadUrl": "https://www.mediafire.com/file/0bjx0xdtdyxs1i6/Etisalat+-+Emirates+Telecommunications+Corporation.zip/file",
    "iconUrl": "https://cdn-icons-png.freepik.com/256/6572/6572271.png?semt=ais_white_label",
    "tag": ""
  }
]
